README
setup.py
bin/bunk
bunk/__init__.py
bunk/core.py
bunk/vault.py
bunk.egg-info/PKG-INFO
bunk.egg-info/SOURCES.txt
bunk.egg-info/dependency_links.txt
bunk.egg-info/requires.txt
bunk.egg-info/top_level.txt