Metadata-Version: 1.1
Name: bunk
Version: 0.1.2
Summary: templating and environment management for kubernetes manifests
Home-page: https://github.com/goblain/bunk
Author: Radek Goblin Pieczonka
Author-email: goblin@pentex.pl
License: MIT
Download-URL: https://github.com/goblain/bunk/tarball/0.1.2.tar.gz
Keywords: kubernetes,templates,environment
Platform: UNKNOWN
